Projeto 03 - MIPS/ADDER.v
/**
 * Universidade Federal Rural de Pernambuco
 * Departamento de Estatística e Informática
 * Disciplina: Arquitetura e Organização de Computadores
 * 
 * Somador de 32 bits.
 *
 * @author André Aziz (andre.caraujo@ufrpe.br)
 */
module ADDER(
 A,
 B,
 O
);

input [31:0] A;
input [31:0] B;
output [31:0] O;

wire [31:0] A;
wire [31:0] B;
wire [31:0] O;

assign O = A + B;

endmodule

Projeto 03 - MIPS/testes/ADDER_tb.v
`include "../ADDER.v"

module ADDER_tb;

reg		[31:0]	A;
reg		[31:0]	B;
wire	[31:0]	O;

initial begin
	$monitor ("A = %d | B = %d | O = %d", A, B, O);
	A = 31'd0;
	B = 31'd0;
	#500 $finish;
end

initial begin
	$dumpfile("ADDER_tb.vcd");
	$dumpvars(0, ADDER_tb, adder);
end

always begin
	#100 A = A + 100000000;
end

always begin
	#10 B = B + 100;
end

ADDER adder (
	.A(A),
	.B(B),
	.O(O)
);

endmodule

Projeto 03 - MIPS/testes/ADDER_tb.vcd
$date
	Tue Jul 17 22:50:35 2018
$end
$version
	Icarus Verilog
$end
$timescale
	1s
$end
$scope module ADDER_tb $end
$var wire 32 ! O [31:0] $end
$var reg 32 " A [31:0] $end
$var reg 32 # B [31:0] $end
$scope module adder $end
$var wire 32 $ A [31:0] $end
$var wire 32 % B [31:0] $end
$var wire 32 & O [31:0] $end
$upscope $end
$upscope $end
$scope module ADDER_tb $end
$scope module adder $end
$upscope $end
$upscope $end
$enddefinitions $end
#0
$dumpvars
b0 &
b0 %
b0 $
b0 #
b0 "
b0 !
$end
#10
b101111101011110000100000000 !
b101111101011110000100000000 &
b101111101011110000100000000 #
b101111101011110000100000000 %
#20
b1011111010111100001000000000 !
b1011111010111100001000000000 &
b1011111010111100001000000000 #
b1011111010111100001000000000 %
#30
b10001111000011010001100000000 !
b10001111000011010001100000000 &
b10001111000011010001100000000 #
b10001111000011010001100000000 %
#40
b10111110101111000010000000000 !
b10111110101111000010000000000 &
b10111110101111000010000000000 #
b10111110101111000010000000000 %
#50
b11101110011010110010100000000 !
b11101110011010110010100000000 &
b11101110011010110010100000000 #
b11101110011010110010100000000 %
#60
b100011110000110100011000000000 !
b100011110000110100011000000000 &
b100011110000110100011000000000 #
b100011110000110100011000000000 %
#70
b101001101110010010011100000000 !
b101001101110010010011100000000 &
b101001101110010010011100000000 #
b101001101110010010011100000000 %
#80
b101111101011110000100000000000 !
b101111101011110000100000000000 &
b101111101011110000100000000000 #
b101111101011110000100000000000 %
#90
b110101101001001110100100000000 !
b110101101001001110100100000000 &
b110101101001001110100100000000 #
b110101101001001110100100000000 %
#100
b111011100110101100101000000000 #
b111011100110101100101000000000 %
b111011100110101100101001100100 !
b111011100110101100101001100100 &
b1100100 "
b1100100 $
#110
b1000001100100001010101101100100 !
b1000001100100001010101101100100 &
b1000001100100001010101100000000 #
b1000001100100001010101100000000 %
#120
b1000111100001101000110001100100 !
b1000111100001101000110001100100 &
b1000111100001101000110000000000 #
b1000111100001101000110000000000 %
#130
b1001101011111000110110101100100 !
b1001101011111000110110101100100 &
b1001101011111000110110100000000 #
b1001101011111000110110100000000 %
#140
b1010011011100100100111001100100 !
b1010011011100100100111001100100 &
b1010011011100100100111000000000 #
b1010011011100100100111000000000 %
#150
b1011001011010000010111101100100 !
b1011001011010000010111101100100 &
b1011001011010000010111100000000 #
b1011001011010000010111100000000 %
#160
b1011111010111100001000001100100 !
b1011111010111100001000001100100 &
b1011111010111100001000000000000 #
b1011111010111100001000000000000 %
#170
b1100101010100111111000101100100 !
b1100101010100111111000101100100 &
b1100101010100111111000100000000 #
b1100101010100111111000100000000 %
#180
b1101011010010011101001001100100 !
b1101011010010011101001001100100 &
b1101011010010011101001000000000 #
b1101011010010011101001000000000 %
#190
b1110001001111111011001101100100 !
b1110001001111111011001101100100 &
b1110001001111111011001100000000 #
b1110001001111111011001100000000 %
#200
b1110111001101011001010000000000 #
b1110111001101011001010000000000 %
b1110111001101011001010011001000 !
b1110111001101011001010011001000 &
b11001000 "
b11001000 $
#210
b1111101001010110111010111001000 !
b1111101001010110111010111001000 &
b1111101001010110111010100000000 #
b1111101001010110111010100000000 %
#220
b10000011001000010101011011001000 !
b10000011001000010101011011001000 &
b10000011001000010101011000000000 #
b10000011001000010101011000000000 %
#230
b10001001000101110011011111001000 !
b10001001000101110011011111001000 &
b10001001000101110011011100000000 #
b10001001000101110011011100000000 %
#240
b10001111000011010001100011001000 !
b10001111000011010001100011001000 &
b10001111000011010001100000000000 #
b10001111000011010001100000000000 %
#250
b10010101000000101111100111001000 !
b10010101000000101111100111001000 &
b10010101000000101111100100000000 #
b10010101000000101111100100000000 %
#260
b10011010111110001101101011001000 !
b10011010111110001101101011001000 &
b10011010111110001101101000000000 #
b10011010111110001101101000000000 %
#270
b10100000111011101011101111001000 !
b10100000111011101011101111001000 &
b10100000111011101011101100000000 #
b10100000111011101011101100000000 %
#280
b10100110111001001001110011001000 !
b10100110111001001001110011001000 &
b10100110111001001001110000000000 #
b10100110111001001001110000000000 %
#290
b10101100110110100111110111001000 !
b10101100110110100111110111001000 &
b10101100110110100111110100000000 #
b10101100110110100111110100000000 %
#300
b10110010110100000101111000000000 #
b10110010110100000101111000000000 %
b10110010110100000101111100101100 !
b10110010110100000101111100101100 &
b100101100 "
b100101100 $
#310
b10111000110001100100000000101100 !
b10111000110001100100000000101100 &
b10111000110001100011111100000000 #
b10111000110001100011111100000000 %
#320
b10111110101111000010000100101100 !
b10111110101111000010000100101100 &
b10111110101111000010000000000000 #
b10111110101111000010000000000000 %
#330
b11000100101100100000001000101100 !
b11000100101100100000001000101100 &
b11000100101100100000000100000000 #
b11000100101100100000000100000000 %
#340
b11001010101001111110001100101100 !
b11001010101001111110001100101100 &
b11001010101001111110001000000000 #
b11001010101001111110001000000000 %
#350
b11010000100111011100010000101100 !
b11010000100111011100010000101100 &
b11010000100111011100001100000000 #
b11010000100111011100001100000000 %
#360
b11010110100100111010010100101100 !
b11010110100100111010010100101100 &
b11010110100100111010010000000000 #
b11010110100100111010010000000000 %
#370
b11011100100010011000011000101100 !
b11011100100010011000011000101100 &
b11011100100010011000010100000000 #
b11011100100010011000010100000000 %
#380
b11100010011111110110011100101100 !
b11100010011111110110011100101100 &
b11100010011111110110011000000000 #
b11100010011111110110011000000000 %
#390
b11101000011101010100100000101100 !
b11101000011101010100100000101100 &
b11101000011101010100011100000000 #
b11101000011101010100011100000000 %
#400
b11101110011010110010100000000000 #
b11101110011010110010100000000000 %
b11101110011010110010100110010000 !
b11101110011010110010100110010000 &
b110010000 "
b110010000 $
#410
b11110100011000010000101010010000 !
b11110100011000010000101010010000 &
b11110100011000010000100100000000 #
b11110100011000010000100100000000 %
#420
b11111010010101101110101110010000 !
b11111010010101101110101110010000 &
b11111010010101101110101000000000 #
b11111010010101101110101000000000 %
#430
b10011001100110010010000 !
b10011001100110010010000 &
b10011001100101100000000 #
b10011001100101100000000 %
#440
b110010000101010110110010000 !
b110010000101010110110010000 &
b110010000101010110000000000 #
b110010000101010110000000000 %
#450
b1100001110001000111010010000 !
b1100001110001000111010010000 &
b1100001110001000110100000000 #
b1100001110001000110100000000 %
#460
b10010001011100110111110010000 !
b10010001011100110111110010000 &
b10010001011100110111000000000 #
b10010001011100110111000000000 %
#470
b11000001001000101000010010000 !
b11000001001000101000010010000 &
b11000001001000100111100000000 #
b11000001001000100111100000000 %
#480
b11110000110100011000110010000 !
b11110000110100011000110010000 &
b11110000110100011000000000000 #
b11110000110100011000000000000 %
#490
b100100000100000001001010010000 !
b100100000100000001001010010000 &
b100100000100000001000100000000 #
b100100000100000001000100000000 %
#500
b101010000001011111001000000000 #
b101010000001011111001000000000 %
b101010000001011111001111110100 !
b101010000001011111001111110100 &
b111110100 "
b111110100 $
